nvxpy/__init__.py
nvxpy/atoms/__init__.py
nvxpy/atoms/abs.py
nvxpy/atoms/amax.py
nvxpy/atoms/amin.py
nvxpy/atoms/cos.py
nvxpy/atoms/det.py
nvxpy/atoms/exp.py
nvxpy/atoms/log.py
nvxpy/atoms/logdet.py
nvxpy/atoms/maximum.py
nvxpy/atoms/minimum.py
nvxpy/atoms/norm.py
nvxpy/atoms/polar.py
nvxpy/atoms/sin.py
nvxpy/atoms/sqrt.py
nvxpy/atoms/sum.py
nvxpy/atoms/trace.py
nvxpy/compiler.py
nvxpy/constants.py
nvxpy/constraint.py
nvxpy/constructs/__init__.py
nvxpy/constructs/function.py
nvxpy/constructs/graph.py
nvxpy/expression.py
nvxpy/overrides.py
nvxpy/parser.py
nvxpy/problem.py
nvxpy/set.py
nvxpy/sets/__init__.py
nvxpy/sets/discrete_set.py
nvxpy/sets/perspective_cone.py
nvxpy/sets/special_orthogonal.py
nvxpy/solvers/__init__.py
nvxpy/solvers/base.py
nvxpy/solvers/bnb/__init__.py
nvxpy/solvers/bnb/backend.py
nvxpy/solvers/bnb/branching.py
nvxpy/solvers/bnb/cuts.py
nvxpy/solvers/bnb/heuristics.py
nvxpy/solvers/bnb/node.py
nvxpy/solvers/bnb/utils.py
nvxpy/solvers/global_scipy_backend.py
nvxpy/solvers/ipopt_backend.py
nvxpy/solvers/scipy_backend.py
nvxpy/variable.py
nvxpy-0.3.0.dist-info/METADATA
nvxpy-0.3.0.dist-info/WHEEL
nvxpy-0.3.0.dist-info/licenses/LICENSE
nvxpy-0.3.0.dist-info/RECORD
