Metadata-Version: 2.4
Name: nvxpy
Version: 0.3.0
Summary: A Python DSL for simply and easily formulating and solving non-convex optimization problems.
License-File: LICENSE
Author: Landon Clark
Author-email: landonclark97@gmail.com
Requires-Python: >=3.11
Classifier: Programming Language :: Python :: 3
Classifier: Programming Language :: Python :: 3.11
Classifier: Programming Language :: Python :: 3.12
Classifier: Programming Language :: Python :: 3.13
Classifier: Programming Language :: Python :: 3.14
Provides-Extra: all
Provides-Extra: ipopt
Requires-Dist: autograd (>=1.8.0,<2.0.0)
Requires-Dist: cyipopt ; extra == "all"
Requires-Dist: cyipopt ; extra == "ipopt"
Requires-Dist: networkx (>=3.6,<4.0)
Requires-Dist: numpy (>=2.3.0,<3.0.0)
Requires-Dist: scipy (>=1.15.3,<2.0.0)
